[
    { "name": "Josh Allen", "position": "QB", "team": "BUF", "fantasy_points": 25.4, "stats": { "total_yards": 3200, "total_touchdowns": 30 } },
    { "name": "Patrick Mahomes", "position": "QB", "team": "KC", "fantasy_points": 25.1, "stats": { "total_yards": 3500, "total_touchdowns": 32 } },
    { "name": "Christian McCaffrey", "position": "RB", "team": "SF", "fantasy_points": 20.5, "stats": { "total_yards": 1800, "total_touchdowns": 15 } },
    { "name": "Davante Adams", "position": "WR", "team": "LV", "fantasy_points": 20.9, "stats": { "total_yards": 1200, "total_touchdowns": 10 } },
    { "name": "Travis Kelce", "position": "TE", "team": "KC", "fantasy_points": 15.0, "stats": { "total_yards": 900, "total_touchdowns": 7 } },
    { "name": "Justin Jefferson", "position": "WR", "team": "MIN", "fantasy_points": 19.1, "stats": { "total_yards": 1300, "total_touchdowns": 9 } },
    { "name": "Derrick Henry", "position": "RB", "team": "BAL", "fantasy_points": 15.8, "stats": { "total_yards": 1400, "total_touchdowns": 12 } },
    { "name": "James Cook", "position": "RB", "team": "BUF", "fantasy_points": 14.2, "stats": { "total_yards": 1100, "total_touchdowns": 8 } },
    { "name": "Tyreek Hill", "position": "WR", "team": "MIA", "fantasy_points": 18.7, "stats": { "total_yards": 1250, "total_touchdowns": 10 } },
    { "name": "Jalen Hurts", "position": "QB", "team": "PHI", "fantasy_points": 22.3, "stats": { "total_yards": 3000, "total_touchdowns": 25 } },
    { "name": "Saquon Barkley", "position": "RB", "team": "PHI", "fantasy_points": 16.5, "stats": { "total_yards": 1300, "total_touchdowns": 10 } },
    { "name": "Stefon Diggs", "position": "WR", "team": "HOU", "fantasy_points": 17.4, "stats": { "total_yards": 1100, "total_touchdowns": 8 } },
    { "name": "Lamar Jackson", "position": "QB", "team": "BAL", "fantasy_points": 23.8, "stats": { "total_yards": 3400, "total_touchdowns": 28 } },
    { "name": "George Kittle", "position": "TE", "team": "SF", "fantasy_points": 13.9, "stats": { "total_yards": 850, "total_touchdowns": 6 } },
    { "name": "CeeDee Lamb", "position": "WR", "team": "DAL", "fantasy_points": 18.2, "stats": { "total_yards": 1150, "total_touchdowns": 9 } },
    { "name": "Joe Burrow", "position": "QB", "team": "CIN", "fantasy_points": 21.6, "stats": { "total_yards": 3300, "total_touchdowns": 27 } },
    { "name": "Bijan Robinson", "position": "RB", "team": "ATL", "fantasy_points": 15.7, "stats": { "total_yards": 1200, "total_touchdowns": 9 } },
    { "name": "A.J. Brown", "position": "WR", "team": "PHI", "fantasy_points": 17.8, "stats": { "total_yards": 1050, "total_touchdowns": 8 } },
    { "name": "Mark Andrews", "position": "TE", "team": "BAL", "fantasy_points": 13.5, "stats": { "total_yards": 800, "total_touchdowns": 6 } },
    { "name": "Kyler Murray", "position": "QB", "team": "ARI", "fantasy_points": 20.4, "stats": { "total_yards": 3100, "total_touchdowns": 24 } },
    { "name": "Jonathan Taylor", "position": "RB", "team": "IND", "fantasy_points": 15.3, "stats": { "total_yards": 1250, "total_touchdowns": 10 } },
    { "name": "Garrett Wilson", "position": "WR", "team": "NYJ", "fantasy_points": 16.9, "stats": { "total_yards": 1000, "total_touchdowns": 7 } },
    { "name": "Sam LaPorta", "position": "TE", "team": "DET", "fantasy_points": 12.8, "stats": { "total_yards": 750, "total_touchdowns": 5 } },
    { "name": "Dak Prescott", "position": "QB", "team": "DAL", "fantasy_points": 20.1, "stats": { "total_yards": 3200, "total_touchdowns": 26 } },
    { "name": "Breece Hall", "position": "RB", "team": "NYJ", "fantasy_points": 16.0, "stats": { "total_yards": 1300, "total_touchdowns": 11 } },
    { "name": "Ja'Marr Chase", "position": "WR", "team": "CIN", "fantasy_points": 18.0, "stats": { "total_yards": 1100, "total_touchdowns": 9 } },
    { "name": "T.J. Hockenson", "position": "TE", "team": "MIN", "fantasy_points": 12.2, "stats": { "total_yards": 700, "total_touchdowns": 5 } },
    { "name": "C.J. Stroud", "position": "QB", "team": "HOU", "fantasy_points": 19.7, "stats": { "total_yards": 3100, "total_touchdowns": 23 } },
    { "name": "Isiah Pacheco", "position": "RB", "team": "KC", "fantasy_points": 14.8, "stats": { "total_yards": 1100, "total_touchdowns": 9 } },
    { "name": "Deebo Samuel", "position": "WR", "team": "SF", "fantasy_points": 16.3, "stats": { "total_yards": 950, "total_touchdowns": 7 } },
    { "name": "Jahmyr Gibbs", "position": "RB", "team": "DET", "fantasy_points": 15.5, "stats": { "total_yards": 1200, "total_touchdowns": 10 } },
    { "name": "Puka Nacua", "position": "WR", "team": "LAR", "fantasy_points": 16.7, "stats": { "total_yards": 1000, "total_touchdowns": 6 } },
    { "name": "Jordan Love", "position": "QB", "team": "GB", "fantasy_points": 19.3, "stats": { "total_yards": 3000, "total_touchdowns": 22 } },
    { "name": "Alvin Kamara", "position": "RB", "team": "NO", "fantasy_points": 14.6, "stats": { "total_yards": 1050, "total_touchdowns": 8 } },
    { "name": "DK Metcalf", "position": "WR", "team": "SEA", "fantasy_points": 16.1, "stats": { "total_yards": 950, "total_touchdowns": 7 } },
    { "name": "Dalton Kincaid", "position": "TE", "team": "BUF", "fantasy_points": 11.9, "stats": { "total_yards": 650, "total_touchdowns": 5 } },
    { "name": "Anthony Richardson", "position": "QB", "team": "IND", "fantasy_points": 18.9, "stats": { "total_yards": 2900, "total_touchdowns": 21 } },
    { "name": "Kenneth Walker III", "position": "RB", "team": "SEA", "fantasy_points": 14.4, "stats": { "total_yards": 1000, "total_touchdowns": 9 } },
    { "name": "Amari Cooper", "position": "WR", "team": "CLE", "fantasy_points": 15.7, "stats": { "total_yards": 900, "total_touchdowns": 6 } },
    { "name": "Evan Engram", "position": "TE", "team": "JAC", "fantasy_points": "11.7", "stats": { "total_yards": 600, "total_touchdowns": 4 } },
    { "name": "Justin Herbert", "position": "QB", "team": "LAC", "fantasy_points": 19.0, "stats": { "total_yards": 3100, "total_touchdowns": 24 } },
    { "name": "Joe Mixon", "position": "RB", "team": "CIN", "fantasy_points": "14.2", "stats": { "total_yards": 950, "total_touchdowns": 8 } },
    { "name": "Mike Evans", "position": "WR", "team": "TB", "fantasy_points": 15.4, "stats": { "total_yards": 900, "total_touchdowns": 6 } },
    { "name": "David Montgomery", "position": "RB", "team": "DET", "fantasy_points": 13.8, "stats": { "total_yards": 900, "total_touchdowns": 7 } },
    { "name": "Cooper Kupp", "position": "WR", "team": "LAR", "fantasy_points": "15.2", "stats": { "total_yards": 850, "total_touchdowns": 6 } },
    { "name": "David Njoku", "position": "TE", "team": "CLE", "fantasy_points": "11.5", "stats": { "total_yards": 550, "total_touchdowns": 4 } },
    { "name": "Trevor Lawrence", "position": "QB", "team": "JAC", "fantasy_points": 18.7, "stats": { "total_yards": 3000, "total_touchdowns": 22 } },
    { "name": "Rhamondre Stevenson", "position": "RB", "team": "NE", "fantasy_points": 14.0, "stats": { "total_yards": 900, "total_touchdowns": 7 } },
    { "name": "Brandon Aiyuk", "position": "WR", "team": "SF", "fantasy_points": 15.0, "stats": { "total_yards": 850, "total_touchdowns": 6 } },
    { "name": "Kyren Williams", "position": "RB", "team": "LAR", "fantasy_points": 13.7, "stats": { "total_yards": 850, "total_touchdowns": 7 } },
    { "name": "Jaylen Waddle", "position": "WR", "team": "MIA", "fantasy_points": 14.8, "stats": { "total_yards": 800, "total_touchdowns": 6 } }
]